Workbook
Name _9_Inches: #REF!

Sheet SALES__DATA
A1: Date Of Sales | B1: Customer Name | C1: Product Type | D1: Qty Sold | E1: Rate | F1: Amount | G1: Bad Debt | H1: Revenue | I1: DAILY | J1: MONTHLY | K1: ANUALLY
A2: 44569 | B2: DAD SEMILORE | C2: 6 Inches | D2: 224 | E2: 250 | F2: =D2*E2 -> 56000 | H2: 56000 | I2: SATURDAY | J2: JANUARY | K2: 2022
A3: 44573 | B3: MR&MRS OMOLERE | C3: 7 Inches | D3: 300 | E3: 260 | F3: =D3*E3 -> 78000 | H3: 78000 | I3: WEDNESDAY | J3: JANUARY | K3: 2022
A4: 44590 | B4: ORIYOMI | C4: 9 Inches | D4: 250 | E4: 295 | F4: =D4*E4 -> 73750 | H4: 73750 | I4: SATURDAY | J4: JANUARY | K4: 2022
A5: 44592 | B5: ORIYOMI | C5: 6 Inches | D5: 500 | E5: 265 | F5: =D5*E5 -> 132500 | H5: 132500 | I5: MONDAY | J5: JANUARY | K5: 2022
A6: 44593 | B6: CSTM@OKO-OPE | C6: 6 Inches | D6: 400 | E6: 260 | F6: =D6*E6 -> 104000 | G6: 1000 | H6: 103000 | I6: TUESDAY | J6: FEBRUARY | K6: 2022
A7: 44596 | B7: MR&MRS OMOLERE | C7: 7 Inches | D7: 150 | E7: 275 | F7: =D7*E7 -> 41250 | G7: 250 | H7: 41000 | I7: FRIDAY | J7: FEBRUARY | K7: 2022
A8: 44597 | B8: Nearby CSTM@OKO-OPE | C8: 6 Inches | D8: 12 | E8: 270 | F8: =D8*E8 -> 3240 | G8: 140 | H8: 3100 | I8: SATURDAY | J8: FEBRUARY | K8: 2022
A9: 44600 | B9: IYA ADURA | C9: 6 Inches | D9: 150 | E9: 260 | F9: =D9*E9 -> 39000 | H9: 39000 | I9: TUESDAY | J9: FEBRUARY | K9: 2022
A10: 44607 | B10: BABA IBEJI BRICK-LAYER | C10: 6 Inches | D10: 25 | E10: 250 | F10: =D10*E10 -> 6250 | H10: 6250 | I10: TUESDAY | J10: FEBRUARY | K10: 2022
A11: 44608 | B11: BABA SAMSON | C11: 7 Inches | D11: 400 | E11: 280 | F11: =D11*E11 -> 112000 | H11: 112000 | I11: WEDNESDAY | J11: FEBRUARY | K11: 2022
A12: 44611 | B12: SERIKI | C12: 6 Inches | D12: 4 | E12: 250 | F12: =D12*E12 -> 1000 | H12: 1000 | I12: SATURDAY | J12: FEBRUARY | K12: 2022
A13: 44616 | B13: BABA IBEJI BRICK-LAYER | C13: 9 Inches | D13: 130 | E13: 300 | F13: =D13*E13 -> 39000 | H13: 39000 | I13: THURSDAY | J13: FEBRUARY | K13: 2022
A14: 44620 | B14: CHURCH ORIOKE | C14: 9 Inches | D14: 12 | E14: 300 | F14: =D14*E14 -> 3600 | H14: 3600 | I14: MONDAY | J14: FEBRUARY | K14: 2022
A15: 44623 | B15: CORNERPIECE | C15: 6 Inches | D15: 2 | E15: 300 | F15: =D15*E15 -> 600 | H15: 600 | I15: THURSDAY | J15: MARCH | K15: 2022
A16: 44625 | B16: BABA SAMSON | C16: 7 Inches | D16: 50 | E16: 330 | F16: =D16*E16 -> 16500 | H16: 16500 | I16: SATURDAY | J16: MARCH | K16: 2022
A17: 44632 | B17: BABA SAMSON | C17: 7 Inches | D17: 50 | E17: 330 | F17: =D17*E17 -> 16500 | H17: 16500 | I17: SATURDAY | J17: MARCH | K17: 2022
A18: 44638 | B18: MR&MRS OMOLERE | C18: 7 Inches | D18: 500 | E18: 320 | F18: =D18*E18 -> 160000 | H18: 160000 | I18: FRIDAY | J18: MARCH | K18: 2022
A19: 44648 | B19: MR&MRS OMOLERE | C19: 7 Inches | D19: 200 | E19: 320 | F19: =D19*E19 -> 64000 | H19: 64000 | I19: MONDAY | J19: MARCH | K19: 2022
A20: 44652 | B20: MR&MRS OMOLERE | C20: 7 Inches | D20: 200 | E20: 320 | F20: =D20*E20 -> 64000 | H20: 64000 | I20: FRIDAY | J20: APRIL | K20: 2022
... A24: 44674 | B24: ALHJ ONAARA | C24: 7 Inches | D24: 60 | E24: 330 | F24: =D24*E24 -> 19800 | H24: 19800 | I24: SATURDAY | J24: APRIL | K24: 2022
A25: 44690 | B25: OLORI | C25: 6 Inches | D25: 16 | E25: 300 | F25: =D25*E25 -> 4800 | G25: 4300 | H25: 500 | I25: MONDAY | J25: MAY | K25: 2022
A26: 44693 | B26: MR&MRS OMOLERE | C26: 7 Inches | D26: 60 | E26: 320 | F26: =D26*E26 -> 19200 | H26: 19200 | I26: THURSDAY | J26: MAY | K26: 2022
A27: 44711 | B27: MR&MRS OMOLERE | C27: 7 Inches | D27: 250 | E27: 320 | F27: =D27*E27 -> 80000 | H27: 80000 | I27: MONDAY | J27: MAY | K27: 2022
A28: 44712 | B28: DAD PRAISE REFERRAL 1 | C28: 6 Inches | D28: 50 | E28: 300 | F28: =D28*E28 -> 15000 | H28: 15000 | I28: TUESDAY | J28: MAY | K28: 2022
A29: 44715 | B29: OGA SANMI | C29: 9 Inches | D29: 400 | E29: 320 | F29: =D29*E29 -> 128000 | H29: 128000 | I29: FRIDAY | J29: JUNE | K29: 2022
A30: 44721 | B30: MR&MRS OMOLERE | C30: 7 Inches | D30: 150 | E30: 320 | F30: =D30*E30 -> 48000 | H30: 48000 | I30: THURSDAY | J30: JUNE | K30: 2022
A31: 44723 | B31: SUPRISE MUMMY | C31: 6 Inches | D31: 16 | E31: 300 | F31: =D31*E31 -> 4800 | H31: 4800 | I31: SATURDAY | J31: JUNE | K31: 2022
A32: 44725 | B32: DAD PRAISE REFERRAL 1 | C32: 6 Inches | D32: 80 | E32: 300 | F32: =D32*E32 -> 24000 | H32: 24000 | I32: MONDAY | J32: JUNE | K32: 2022
A33: 44726 | B33: DAD PRAISE REFERRAL 1 | C33: 6 Inches | D33: 40 | E33: 300 | F33: =D33*E33 -> 12000 | H33: 12000 | I33: TUESDAY | J33: JUNE | K33: 2022
A34: 44730 | B34: DAD PRAISE REFERRAL 1 | C34: 6 Inches | D34: 20 | E34: 300 | F34: =D34*E34 -> 6000 | H34: 6000 | I34: SATURDAY | J34: JUNE | K34: 2022
A35: 44758 | B35: CSTM@OKO-OPE | C35: 6 Inches | D35: 500 | E35: 330 | F35: =D35*E35 -> 165000 | G35: 5000 | H35: 160000 | I35: SATURDAY | J35: JULY | K35: 2022
A36: 44769 | B36: ADEBISI SCH. | C36: 6 Inches | D36: 100 | E36: 300 | F36: =D36*E36 -> 30000 | H36: 30000 | I36: WEDNESDAY | J36: JULY | K36: 2022
A37: 44792 | B37: ENG. WAHEED | C37: 9 Inches | D37: 3800 | E37: 350 | F37: =D37*E37 -> 1330000 | H37: 1330000 | I37: FRIDAY | J37: AUGUST | K37: 2022
A38: 44792 | B38: ENG. WAHEED | C38: 6 Inches | D38: 800 | E38: 330 | F38: =D38*E38 -> 264000 | H38: 264000 | I38: FRIDAY | J38: AUGUST | K38: 2022
A39: 44813 | B39: ADEBISI SCH. | C39: 6 Inches | D39: 100 | E39: 300 | F39: =D39*E39 -> 30000 | H39: 30000 | I39: FRIDAY | J39: SEPTEMBER | K39: 2022
A40: 44814 | B40: BRICKLAYER CONERPIEC 1 | C40: 6 Inches | D40: 16 | E40: 330 | F40: =D40*E40 -> 5280 | H40: 5280 | I40: SATURDAY | J40: SEPTEMBER | K40: 2022
A41: 44816 | B41: ENG. WAHEED | C41: 9 Inches | D41: 50 | E41: 350 | F41: =D41*E41 -> 17500 | G41: 17500 | H41: 0 | I41: MONDAY | J41: SEPTEMBER | K41: 2022
A42: 44816 | B42: ENG. WAHEED | C42: 7 Inches | D42: 220 | E42: 340 | F42: =D42*E42 -> 74800 | H42: 74800 | I42: MONDAY | J42: SEPTEMBER | K42: 2022
A43: 44818 | B43: ENG. WAHEED | C43: 6 Inches | D43: 450 | E43: 330 | F43: =D43*E43 -> 148500 | H43: 148500 | I43: WEDNESDAY | J43: SEPTEMBER | K43: 2022
A44: 44818 | B44: ENG. WAHEED | C44: 9 Inches | D44: 60 | E44: 350 | F44: =D44*E44 -> 21000 | H44: 21000 | I44: WEDNESDAY | J44: SEPTEMBER | K44: 2022
A45: 44823 | B45: BRICKLAYER CONERPICE 2 | C45: 6 Inches | D45: 8 | E45: 350 | F45: =D45*E45 -> 2800 | H45: 2800 | I45: MONDAY | J45: SEPTEMBER | K45: 2022
A46: 44831 | B46: DAD PRAISE REFERRAL 1 | C46: 6 Inches | D46: 40 | E46: 320 | F46: =D46*E46 -> 12800 | H46: 12800 | I46: TUESDAY | J46: SEPTEMBER | K46: 2022
A47: 44831 | B47: DAD PRAISE REFERRAL 1 | C47: 9 Inches | D47: 10 | E47: 350 | F47: =D47*E47 -> 3500 | G47: 700 | H47: 2800 | I47: TUESDAY | J47: SEPTEMBER | K47: 2022
A48: 44840 | B48: SURVEYOR SAMBEST | C48: 7 Inches | D48: 400 | E48: 370 | F48: =D48*E48 -> 148000 | G48: 8000 | H48: 140000 | I48: THURSDAY | J48: OCTOBER | K48: 2022
A49: 44840 | B49: ENG. WAHEED | C49: 6 Inches | D49: 170 | E49: 330 | F49: =D49*E49 -> 56100 | H49: 56100 | I49: THURSDAY | J49: OCTOBER | K49: 2022
A50: 44840 | B50: ENG. WAHEED | C50: 7 Inches | D50: 70 | E50: 340 | F50: =D50*E50 -> 23800 | H50: 23800 | I50: THURSDAY | J50: OCTOBER | K50: 2022
A51: 44840 | B51: ENG. WAHEED | C51: 9 Inches | D51: 90 | E51: 350 | F51: =D51*E51 -> 31500 | H51: 31500 | I51: THURSDAY | J51: OCTOBER | K51: 2022
A52: 44840 | B52: NEPA CSTM | C52: 9 Inches | D52: 150 | E52: 390 | F52: =D52*E52 -> 58500 | H52: 58500 | I52: THURSDAY | J52: OCTOBER | K52: 2022
A53: 44845 | B53: IYA IZOBO REFERRAL 1 | C53: 6 Inches | D53: 300 | E53: 350 | F53: =D53*E53 -> 105000 | H53: 105000 | I53: TUESDAY | J53: OCTOBER | K53: 2022
A54: 44847 | B54: DAD PRAISE REFERRAL 3 | C54: 9 Inches | D54: 400 | E54: 380 | F54: =D54*E54 -> 152000 | H54: 152000 | I54: THURSDAY | J54: OCTOBER | K54: 2022
A55: 44851 | B55: DAD PRAISE REFERRAL 3 | C55: 6 Inches | D55: 500 | E55: 330 | F55: =D55*E55 -> 165000 | H55: 165000 | I55: MONDAY | J55: OCTOBER | K55: 2022
A56: 44852 | B56: DAD PRAISE REFERRAL 3 | C56: 6 Inches | D56: 200 | E56: 330 | F56: =D56*E56 -> 66000 | H56: 66000 | I56: TUESDAY | J56: OCTOBER | K56: 2022
A57: 44852 | B57: DAD PRAISE REFERRAL 3 | C57: 9 Inches | D57: 300 | E57: 380 | F57: =D57*E57 -> 114000 | H57: 114000 | I57: TUESDAY | J57: OCTOBER | K57: 2022
A58: 44852 | B58: DAD PRAISE | C58: 6 Inches | D58: 200 | E58: 300 | F58: =D58*E58 -> 60000 | G58: 40000 | H58: 20000 | I58: TUESDAY | J58: OCTOBER | K58: 2022
A59: 44855 | B59: DAD PRAISE REFERRAL 3 | C59: 6 Inches | D59: 300 | E59: 330 | F59: =D59*E59 -> 99000 | H59: 99000 | I59: FRIDAY | J59: OCTOBER | K59: 2022
A60: 44855 | B60: DAD PRAISE REFERRAL 3 | C60: 9 Inches | D60: 280 | E60: 380 | F60: =D60*E60 -> 106400 | H60: 106400 | I60: FRIDAY | J60: OCTOBER | K60: 2022
A61: 44858 | B61: NEPA CSTM | C61: 9 Inches | D61: 100 | E61: 390 | F61: =D61*E61 -> 39000 | H61: 39000 | I61: MONDAY | J61: OCTOBER | K61: 2022
A62: 44867 | B62: DAD PRAISE REFERRAL 3 | C62: 6 Inches | D62: 150 | E62: 330 | F62: =D62*E62 -> 49500 | H62: 49500 | I62: WEDNESDAY | J62: NOVEMBER | K62: 2022
A63: 44868 | B63: DAD PRAISE REFERRAL 2 | C63: 9 Inches | D63: 600 | E63: 380 | F63: =D63*E63 -> 228000 | H63: 228000 | I63: THURSDAY | J63: NOVEMBER | K63: 2022
A64: 44879 | B64: BABA OLOKO CSTM | C64: 6 Inches | D64: 150 | E64: 350 | F64: =D64*E64 -> 52500 | H64: 52500 | I64: MONDAY | J64: NOVEMBER | K64: 2022
A65: 44880 | B65: BABA OLOKO CSTM | C65: 6 Inches | D65: 100 | E65: 350 | F65: =D65*E65 -> 35000 | H65: 35000 | I65: TUESDAY | J65: NOVEMBER | K65: 2022
A66: 44894 | B66: NEPA CSTM | C66: 9 Inches | D66: 150 | E66: 400 | F66: =D66*E66 -> 60000 | H66: 60000 | I66: TUESDAY | J66: NOVEMBER | K66: 2022
A67: 44909 | B67: GBAJUE CSTM | C67: 6 Inches | D67: 19 | E67: 370 | F67: =D67*E67 -> 7030 | G67: 30 | H67: 7000 | I67: WEDNESDAY | J67: DECEMBER | K67: 2022
A68: 44910 | B68: CSTM. ISMAIL | C68: 6 Inches | D68: 200 | E68: 370 | F68: =D68*E68 -> 74000 | H68: 74000 | I68: THURSDAY | J68: DECEMBER | K68: 2022
A69: 44911 | B69: ENG. WAHEED | C69: 7 Inches | D69: 130 | E69: 380 | F69: =D69*E69 -> 49400 | H69: 49400 | I69: FRIDAY | J69: DECEMBER | K69: 2022
A70: 44911 | B70: CSTM. ISMAIL | C70: 6 Inches | D70: 300 | E70: 370 | F70: =D70*E70 -> 111000 | H70: 111000 | I70: FRIDAY | J70: DECEMBER | K70: 2022
A71: 44911 | B71: CSTM. ISMAIL | C71: 9 Inches | D71: 300 | E71: 400 | F71: =D71*E71 -> 120000 | H71: 120000 | I71: FRIDAY | J71: DECEMBER | K71: 2022
A72: 44913 | B72: AYO CSTM | C72: 7 Inches | D72: 30 | E72: 390 | F72: =D72*E72 -> 11700 | G72: 200 | H72: 11500 | I72: SUNDAY | J72: DECEMBER | K72: 2022
A73: 44915 | B73: CSTM. ISMAIL | C73: 6 Inches | D73: 100 | E73: 370 | F73: =D73*E73 -> 37000 | H73: 37000 | I73: TUESDAY | J73: DECEMBER | K73: 2022
A74: 44916 | B74: CSTM. ISMAIL | C74: 6 Inches | D74: 200 | E74: 370 | F74: =D74*E74 -> 74000 | H74: 74000 | I74: WEDNESDAY | J74: DECEMBER | K74: 2022
A75: 44917 | B75: JAWA CSTM | C75: 9 Inches | D75: 50 | E75: 400 | F75: =D75*E75 -> 20000 | H75: 20000 | I75: THURSDAY | J75: DECEMBER | K75: 2022
A76: 44920 | B76: CSTM. ISMAIL | C76: 6 Inches | D76: 30 | E76: 370 | F76: =D76*E76 -> 11100 | H76: 11100 | I76: SUNDAY | J76: DECEMBER | K76: 2022
A77: 44920 | B77: MOSHOOD JOSEPH | C77: 9 Inches | D77: 75 | E77: 360 | F77: =D77*E77 -> 27000 | H77: 27000 | I77: SUNDAY | J77: DECEMBER | K77: 2022
A78: 44921 | B78: ENG. WAHEED | C78: 7 Inches | D78: 100 | E78: 380 | F78: =D78*E78 -> 38000 | H78: 38000 | I78: MONDAY | J78: DECEMBER | K78: 2022
A79: 44930 | B79: BISHOP BRICKLAYER | C79: 6 Inches | D79: 300 | E79: 350 | F79: =D79*E79 -> 105000 | H79: 105000 | I79: WEDNESDAY | J79: JANUARY | K79: 2023
A80: 44932 | B80: MOSHOOD JOSEPH | C80: 9 Inches | D80: 34 | E80: 360 | F80: =D80*E80 -> 12240 | H80: 12240 | I80: FRIDAY | J80: JANUARY | K80: 2023
A81: 44935 | B81: BISHOP BRICKLAYER | C81: 9 Inches | D81: 100 | E81: 390 | F81: =D81*E81 -> 39000 | H81: 39000 | I81: MONDAY | J81: JANUARY | K81: 2023
A82: 44937 | B82: BISHOP BRICKLAYER | C82: 6 Inches | D82: 100 | E82: 350 | F82: =D82*E82 -> 35000 | H82: 35000 | I82: WEDNESDAY | J82: JANUARY | K82: 2023
A83: 44938 | B83: SUPRISE MUMMY FRIEND | C83: 6 Inches | D83: 16 | E83: 380 | F83: =D83*E83 -> 6080 | H83: 6080 | I83: THURSDAY | J83: JANUARY | K83: 2023
A84: 44950 | B84: DAD PRAISE REFERRAL 4 | C84: 9 Inches | D84: 400 | E84: 385 | F84: =D84*E84 -> 154000 | H84: 154000 | I84: TUESDAY | J84: JANUARY | K84: 2023
A85: 44987 | B85: D.P.R.3 BRICKLAYER | C85: 9 Inches | D85: 60 | E85: 410 | F85: =D85*E85 -> 24600 | G85: 100 | H85: 24500 | I85: THURSDAY | J85: MARCH | K85: 2023
A86: 45005 | B86: CSTM ATOYEBI FARUQ | C86: 9 Inches | D86: 1000 | E86: 400 | F86: =D86*E86 -> 400000 | H86: 400000 | I86: MONDAY | J86: MARCH | K86: 2023
A87: 45005 | B87: CSTM AJEIGBE | C87: 6 Inches | D87: 16 | E87: 350 | F87: =D87*E87 -> 5600 | H87: 5600 | I87: MONDAY | J87: MARCH | K87: 2023
A88: 45007 | B88: IYA SODIQ | C88: 6 Inches | D88: 15 | E88: 350 | F88: =D88*E88 -> 5250 | H88: 5250 | I88: WEDNESDAY | J88: MARCH | K88: 2023
A89: 45009 | B89: SURVEYOR CSTM | C89: 6 Inches | D89: 25 | E89: 350 | F89: =D89*E89 -> 8750 | H89: 8750 | I89: FRIDAY | J89: MARCH | K89: 2023
A90: 45015 | B90: CSTM ATOYEBI FARUQ | C90: 9 Inches | D90: 300 | E90: 400 | F90: =D90*E90 -> 120000 | H90: 120000 | I90: THURSDAY | J90: MARCH | K90: 2023
A91: 45016 | B91: CSTM ATOYEBI FARUQ | C91: 9 Inches | D91: 200 | E91: 400 | F91: =D91*E91 -> 80000 | H91: 80000 | I91: FRIDAY | J91: MARCH | K91: 2023
A92: 45017 | B92: CSTM ATOYEBI FARUQ | C92: 9 Inches | D92: 100 | E92: 400 | F92: =D92*E92 -> 40000 | H92: 40000 | I92: SATURDAY | J92: APRIL | K92: 2023
A93: 45021 | B93: MR JEREMIAH | C93: 6 Inches | D93: 16 | E93: 340 | F93: =D93*E93 -> 5440 | H93: 5440 | I93: WEDNESDAY | J93: APRIL | K93: 2023
A94: 45024 | B94: ALHAJA CSTM RFRL 1 | C94: 6 Inches | D94: 50 | E94: 350 | F94: =D94*E94 -> 17500 | H94: 17500 | I94: SATURDAY | J94: APRIL | K94: 2023
A95: 45024 | B95: ALHAJA CSTM RFRL 1 | C95: 9 Inches | D95: 25 | E95: 400 | F95: =D95*E95 -> 10000 | H95: 10000 | I95: SATURDAY | J95: APRIL | K95: 2023
A96: 45026 | B96: ALHAJA CSTM RFRL 2 | C96: 6 Inches | D96: 40 | E96: 350 | F96: =D96*E96 -> 14000 | H96: 14000 | I96: MONDAY | J96: APRIL | K96: 2023
A97: 45027 | B97: CSTM TEMITOPE | C97: 6 Inches | D97: 200 | E97: 360 | F97: =D97*E97 -> 72000 | H97: 72000 | I97: TUESDAY | J97: APRIL | K97: 2023
A98: 45027 | B98: MR JEREMIAH | C98: 6 Inches | D98: 400 | E98: 330 | F98: =D98*E98 -> 132000 | H98: 132000 | I98: TUESDAY | J98: APRIL | K98: 2023
A99: 45028 | B99: MR&MRS OMOLERE | C99: 7 Inches | D99: 2500 | E99: 302 | F99: =D99*E99 -> 755000 | G99: 50000 | H99: 705000 | I99: WEDNESDAY | J99: APRIL | K99: 2023
A100: 45031 | B100: MR ADEBAYO/NICE CSTM | C100: 9 Inches | D100: 50 | E100: 400 | F100: =D100*E100 -> 20000 | H100: 20000 | I100: SATURDAY | J100: APRIL | K100: 2023
A101: 45055 | B101: IJIKU POULTRY CSTM | C101: 6 Inches | D101: 400 | E101: 350 | F101: =D101*E101 -> 140000 | H101: 140000 | I101: TUESDAY | J101: MAY | K101: 2023
A102: 45068 | B102: MR LUKMAN NEIGHBOUR | C102: 6 Inches | D102: 50 | E102: 380 | F102: =D102*E102 -> 19000 | H102: 19000 | I102: MONDAY | J102: MAY | K102: 2023
A103: 45076 | B103: BABA ASOLO | C103: 9 Inches | D103: 315 | E103: 350 | F103: =D103*E103 -> 110250 | H103: 110250 | I103: TUESDAY | J103: MAY | K103: 2023
...

Sheet PRODUCTION_DATA
A1: Date | B1: 6 Inches Qty | C1: 7 Inches Qty | D1: 9 Inches Qty | E1: Total Qty Produced | F1: Total Qty Sold | G1: Tons Of Sand | H1: Bags of Cement | I1: Bag Produced | J1: Ltr. Of Fuel | K1: Sand Cost | L1: Cement Cost | M1: Operators' Payment | N1: Fuel Cost | O1: Maintenance | P1: Delivery Cost | Q1: Total Revenue | R1: Total Cost | S1: Total Profit | T1: Bad Debt | U1: MONTHLY | V1: ANUALLY
A2: 44531 | B2: 1020 | C2: 500 | D2: 336 | E2: 1856 | G2: 30 | H2: 35 | I2: 35 | J2: 25 | K2: 90000 | L2: 140000 | M2: 42000 | N2: 4125 | R2: 276125 | S2: -276125 | U2: DEC | V2: 2021
A3: 44562 | F3: 1274 | P3: 63700 | Q3: 340250 | R3: 63700 | S3: 276550 | U3: JAN | V3: 2022
A4: 44593 | B4: 900 | C4: 1250 | D4: 210 | E4: 2360 | F4: 1283 | G4: 48 | H4: 45 | I4: 45 | J4: 24 | K4: 147500 | L4: 189000 | M4: 67500 | N4: 4000 | P4: 64150 | Q4: 347950 | R4: 472150 | S4: -124200 | T4: 1390 | U4: FEB | V4: 2022
A5: 44621 | B5: 440 | C5: 96 | D5: 252 | E5: 788 | F5: 802 | G5: 20 | H5: 29 | I5: 16 | J5: 24 | K5: 70000 | L5: 119400 | M5: 22400 | N5: 4000 | P5: 40100 | Q5: 257600 | R5: 255900 | S5: 1700 | U5: MAR | V5: 2022
A6: 44652 | C6: 700 | D6: 798 | E6: 1498 | F6: 1560 | G6: 30 | H6: 22 | I6: 33 | J6: 27 | K6: 120000 | L6: 90000 | M6: 48000 | N6: 4400 | P6: 78000 | Q6: 521800 | R6: 340400 | S6: 181400 | U6: APR | V6: 2022
A7: 44682 | C7: 546 | E7: 546 | F7: 376 | G7: 10 | H7: 10 | I7: 11 | J7: 12 | K7: 40000 | L7: 40000 | M7: 15000 | N7: 2000 | P7: 18800 | Q7: 114700 | R7: 115800 | S7: -1100 | T7: 4300 | U7: MAY | V7: 2022
A8: 44713 | D8: 645 | E8: 645 | F8: 706 | G8: 30 | H8: 20 | I8: 15 | J8: 12 | K8: 120000 | L8: 82000 | M8: 22500 | N8: 2000 | P8: 35300 | Q8: 222800 | R8: 261800 | S8: -39000 | U8: JUN | V8: 2022
A9: 44743 | B9: 780 | E9: 780 | F9: 600 | G9: 10 | H9: 12 | I9: 13 | J9: 12 | K9: 50000 | L9: 45700 | M9: 15000 | N9: 2000 | P9: 30000 | Q9: 190000 | R9: 142700 | S9: 47300 | T9: 5000 | U9: JUL | V9: 2022
A10: 44774 | B10: 569 | D10: 3226 | E10: 3795 | F10: 4600 | G10: 100 | H10: 86 | I10: 86 | J10: 61 | K10: 500000 | L10: 348300 | M10: 129000 | N10: 10000 | O10: 77900 | P10: 230000 | Q10: 1594000 | R10: 1295200 | S10: 298800 | U10: AUG | V10: 2022
A11: 44805 | B11: 1320 | C11: 450 | D11: 516 | E11: 2286 | F11: 954 | G11: 20 | H11: 53 | I11: 48 | J11: 48 | K11: 100000 | L11: 214650 | M11: 72000 | N11: 8000 | O11: 2000 | P11: 47700 | Q11: 297980 | R11: 444350 | S11: -146370 | T11: 18200 | U11: SEP | V11: 2022
A12: 44835 | B12: 1740 | C12: 400 | D12: 1634 | E12: 3774 | F12: 3460 | G12: 90 | H12: 70 | I12: 75 | J12: 48 | K12: 435000 | L12: 283500 | M12: 112500 | N12: 8000 | O12: 5500 | P12: 173000 | Q12: 1176300 | R12: 1017500 | S12: 158800 | T12: 48000 | U12: OCT | V12: 2022
A13: 44866 | D13: 430 | E13: 430 | F13: 1150 | G13: 10 | H13: 10 | I13: 10 | J13: 24 | K13: 50000 | L13: 40500 | M13: 15000 | N13: 4000 | O13: 5000 | P13: 57500 | Q13: 425000 | R13: 172000 | S13: 253000 | U13: NOV | V13: 2022
A14: 44896 | B14: 840 | D14: 817 | E14: 1657 | F14: 1534 | G14: 60 | H14: 33 | I14: 33 | J14: 30 | K14: 225000 | L14: 155100 | M14: 49500 | N14: 5000 | P14: 76700 | Q14: 580000 | R14: 511300 | S14: 68700 | T14: 230 | U14: DEC | V14: 2022
A15: 44927 | B15: 480 | D15: 344 | E15: 824 | F15: 950 | G15: 18 | H15: 18 | I15: 16 | J15: 20 | K15: 87500 | L15: 86400 | M15: 24000 | N15: 4000 | P15: 57000 | Q15: 351320 | R15: 258900 | S15: 92420 | U15: JAN | V15: 2023
A16: 44958 | V16: 2023
A17: 44986 | B17: 420 | D17: 1591 | E17: 2011 | F17: 1616 | G17: 38 | H17: 44 | I17: 44 | J17: 39 | K17: 187500 | L17: 209000 | M17: 66000 | N17: 7500 | O17: 2000 | P17: 96960 | Q17: 644100 | R17: 568960 | S17: 75140 | T17: 100 | U17: MAR | V17: 2023
A18: 45017 | B18: 900 | C18: 2500 | D18: 215 | E18: 3615 | F18: 3381 | G18: 72 | H18: 70 | I18: 70 | J18: 56 | K18: 362500 | L18: 328900 | M18: 120000 | N18: 11030 | O18: 2000 | P18: 52860 | Q18: 1015940 | R18: 877290 | S18: 138650 | T18: 50000 | U18: APR | V18: 2023
A19: 45047 | B19: 303 | C19: 201 | E19: 504 | F19: 1642 | G19: 8 | H19: 7 | I19: 6 | J19: 8 | K19: 37500 | L19: 32900 | M19: 9000 | N19: 1500 | P19: 98520 | Q19: 584200 | R19: 179420 | S19: 404780 | U19: MAY | V19: 2023
A20: 45078 | D20: 760 | E20: 760 | F20: 870 | G20: 42 | H20: 20 | I20: 20 | J20: 8 | K20: 212500 | L20: 145500 | M20: 30000 | N20: 2000 | P20: 52200 | Q20: 343200 | R20: 442200 | S20: -99000 | U20: JUN | V20: 2023
A21: 45108 | D21: 903 | E21: 903 | F21: 470 | G21: 28 | H21: 27 | I21: 21 | J21: 14 | K21: 137500 | L21: 135300 | M21: 32000 | N21: 7470 | O21: 20200 | P21: 28200 | Q21: 181500 | R21: 360670 | S21: -179170 | U21: JUL | V21: 2023
A22: 45139 | B22: 480 | D22: 560 | E22: 1040 | F22: 440 | G22: 25 | H22: 16 | I22: 21 | J22: 6 | K22: 125000 | L22: 87200 | M22: 33500 | N22: 3480 | P22: 26400 | Q22: 182200 | R22: 275580 | S22: -93380 | T22: 1000 | U22: AUG | V22: 2023
A23: 45170 | B23: 660 | D23: 1419 | E23: 2079 | F23: 1928 | G23: 48 | H23: 43 | I23: 44 | J23: 22 | K23: 237500 | L23: 230050 | M23: 74800 | N23: 12800 | O23: 20000 | P23: 115680 | Q23: 841200 | R23: 690830 | S23: 150370 | U23: SEP | V23: 2023
A24: 45200 | B24: 1920 | D24: 860 | E24: 2780 | F24: 2838 | G24: 65 | H24: 53 | I24: 52 | J24: 26 | K24: 360000 | L24: 283550 | M24: 138600 | N24: 15600 | O24: 3000 | P24: 170280 | Q24: 1255440 | R24: 971030 | S24: 284410 | T24: 2150 | U24: OCT | V24: 2023
A25: 45231 | B25: 1140 | E25: 1140 | F25: 982 | G25: 18 | H25: 18 | I25: 19 | J25: 8 | K25: 100000 | L25: 98100 | M25: 32300 | N25: 4800 | O25: 1500 | P25: 58920 | Q25: 446900 | R25: 295620 | S25: 151280 | U25: NOV | V25: 2023
A26: 45261 | B26: 840 | D26: 817 | E26: 1657 | F26: 1505 | G26: 50 | H26: 33 | I26: 33 | J26: 26 | K26: 300000 | L26: 179850 | M26: 56100 | N26: 16000 | O26: 4000 | P26: 90300 | Q26: 710450 | R26: 646250 | S26: 64200 | U26: DEC | V26: 2023
A27: 45292 | F27: 720 | G27: 8 | K27: 45000 | O27: 10000 | P27: 50400 | Q27: 294000 | R27: 105400 | S27: 188600 | U27: JAN | V27: 2024
A28: 45323 | B28: 1560 | C28: 20 | D28: 430 | E28: 2010 | F28: 2020 | G28: 45 | H28: 40 | I28: 40 | J28: 16 | K28: 270000 | L28: 435800 | M28: 78000 | N28: 10000 | P28: 141400 | Q28: 1120000 | R28: 935200 | S28: 184800 | U28: FEB | V28: 2024
A29: 45352 | F29: 347 | G29: 10 | K29: 85000 | P29: 24290 | Q29: 236350 | R29: 109290 | S29: 127060 | U29: MAR | V29: 2024
A30: 45383 | F30: 173 | P30: 12110 | Q30: 129060 | R30: 12110 | S30: 116950 | U30: APR | V30: 2024
A31: 45413 | V31: 2024
A32: 45444 | F32: 16 | P32: 1120 | Q32: 11200 | S32: 11200 | V32: 2024
A33: 45474 | V33: 2024
A34: 45505 | V34: 2024
A35: 45536 | V35: 2024
A36: 45566 | V36: 2024
A37: 45597 | V37: 2024
A38: 45627 | V38: 2024
A39: 45658 | V39: 2025
A40: 45689 | V40: 2025
A41: 45717 | V41: 2025
A42: 45748 | V42: 2025
A43: 45778 | B43: 960 | D43: 566 | E43: 1526 | G43: 10 | H43: 35 | I43: 29 | J43: 25 | K43: 100000 | L43: 367500 | M43: 87000 | N43: 22250 | O43: 237700 | R43: 814450 | S43: -814450 | U43: MAY | V43: 2025
A44: 45809 | F44: 925 | P44: 69375 | Q44: 760000 | R44: 69375 | S44: 690625 | U44: JUN | V44: 2025
A45: 45839 | B45: 1184 | D45: 472 | E45: 1656 | F45: 850 | G45: 30 | H45: 25 | I45: 29 | J45: 22 | K45: 300000 | L45: 265500 | M45: 92000 | N45: 20000 | P45: 63750 | Q45: 762500 | R45: 741250 | S45: 21250 | U45: JUL | V45: 2025
A46: 45870 | F46: 377 | P46: 23550 | Q46: 290300 | R46: 23550 | S46: 266750 | T46: 50400 | U46: AUG | V46: 2025
A47: 45901 | F47: 550 | G47: 10 | K47: 100000 | P47: 41250 | Q47: 436500 | R47: 141250 | S47: 295250 | U47: SEP | V47: 2025
A48: 45931 | B48: 584 | E48: 584 | F48: 414 | H48: 12 | I48: 10 | J48: 11 | L48: 122400 | M48: 30000 | N48: 10000 | O48: 80000 | P48: 31050 | Q48: 359700 | R48: 273450 | S48: 86250 | T48: 5000 | U48: OCT | V48: 2025
A49: 45962 | B49: 1558 | D49: 817 | E49: 2375 | F49: 1131 | G49: 60 | H49: 39 | I49: 42 | J49: 36 | K49: 510000 | L49: 401700 | M49: 142000 | N49: 32500 | O49: 64000 | P49: 84825 | Q49: 885500 | R49: 1235025 | S49: -349525 | U49: NOV | V49: 2025
A50: 45992 | F50: 786 | P50: 58950 | Q50: 723600 | R50: 58950 | S50: 664650 | U50: DEC | V50: 2025

Sheet TIME OF PRODUCTION
A5: Row Labels | B5: Sum of Total Qty Produced | C5: Sum of Total Cost | E5: COST per unit = TOTAL COST / TOTAL QTY PRODUCED | L5: PRODUCTION EFFICIENCY = QTY_PRODUCED / TOTAL_COST
A6: 2021 | B6: 1856 | C6: 276125 | G6: =SUM(C6/B6) -> 148.77425 | L6: =GETPIVOTDATA("[Measures].[Sum of Total Qty Produced]",$A$5,"[Range].[ANUALLY]","[Range].[ANUALLY].&[2021]")/GETPIVOTDATA("[Measures].[Sum of Total Cost]",$A$5,"[Range].[ANUALLY]","[Range].[ANUALLY].&[2021]") -> 0.0067215935
A7: DEC | B7: 1856 | C7: 276125 | G7: =SUM(C7/B7) -> 148.77425
A8: 2022 | B8: 18559 | C8: 5092800 | G8: =SUM(C8/B8) -> 274.41134 | L8: =GETPIVOTDATA("[Measures].[Sum of Total Qty Produced]",$A$5,"[Range].[ANUALLY]","[Range].[ANUALLY].&[2022]")/GETPIVOTDATA("[Measures].[Sum of Total Cost]",$A$5,"[Range].[ANUALLY]","[Range].[ANUALLY].&[2022]") -> 0.0036441643
A9: JAN | C9: 63700 | G9: =SUM(C9/B9) -> #DIV/0!
A10: FEB | B10: 2360 | C10: 472150 | G10: =SUM(C10/B10) -> 200.06356
A11: MAR | B11: 788 | C11: 255900 | G11: =SUM(C11/B11) -> 324.74619
A12: APR | B12: 1498 | C12: 340400 | G12: =SUM(C12/B12) -> 227.23632
A13: MAY | B13: 546 | C13: 115800 | G13: =SUM(C13/B13) -> 212.08791
A14: JUN | B14: 645 | C14: 261800 | G14: =SUM(C14/B14) -> 405.89147
A15: JUL | B15: 780 | C15: 142700 | G15: =SUM(C15/B15) -> 182.94872
A16: AUG | B16: 3795 | C16: 1295200 | G16: =SUM(C16/B16) -> 341.29117
A17: SEP | B17: 2286 | C17: 444350 | G17: =SUM(C17/B17) -> 194.37883
A18: OCT | B18: 3774 | C18: 1017500 | G18: =SUM(C18/B18) -> 269.60784
A19: NOV | B19: 430 | C19: 172000 | G19: =SUM(C19/B19) -> 400
A20: DEC | B20: 1657 | C20: 511300 | G20: =SUM(C20/B20) -> 308.5697
A21: 2023 | B21: 17313 | C21: 5566750 | G21: =SUM(C21/B21) -> 321.53584 | L21: =GETPIVOTDATA("[Measures].[Sum of Total Qty Produced]",$A$5,"[Range].[ANUALLY]","[Range].[ANUALLY].&[2023]")/GETPIVOTDATA("[Measures].[Sum of Total Cost]",$A$5,"[Range].[ANUALLY]","[Range].[ANUALLY].&[2023]") -> 0.0031100732
A22: JAN | B22: 824 | C22: 258900 | G22: =SUM(C22/B22) -> 314.19903
A23: MAR | B23: 2011 | C23: 568960 | G23: =SUM(C23/B23) -> 282.92392
A24: APR | B24: 3615 | C24: 877290 | G24: =SUM(C24/B24) -> 242.6805
A25: MAY | B25: 504 | C25: 179420 | G25: =SUM(C25/B25) -> 355.99206
A26: JUN | B26: 760 | C26: 442200 | G26: =SUM(C26/B26) -> 581.84211
A27: JUL | B27: 903 | C27: 360670 | G27: =SUM(C27/B27) -> 399.41307
A28: AUG | B28: 1040 | C28: 275580 | G28: =SUM(C28/B28) -> 264.98077
A29: SEP | B29: 2079 | C29: 690830 | G29: =SUM(C29/B29) -> 332.28956
A30: OCT | B30: 2780 | C30: 971030 | G30: =SUM(C30/B30) -> 349.29137
A31: NOV | B31: 1140 | C31: 295620 | G31: =SUM(C31/B31) -> 259.31579
A32: DEC | B32: 1657 | C32: 646250 | G32: =SUM(C32/B32) -> 390.01207
A33: 2024 | B33: 2010 | C33: 1162000 | G33: =SUM(C33/B33) -> 578.10945 | L33: =GETPIVOTDATA("[Measures].[Sum of Total Qty Produced]",$A$5,"[Range].[ANUALLY]","[Range].[ANUALLY].&[2024]")/GETPIVOTDATA("[Measures].[Sum of Total Cost]",$A$5,"[Range].[ANUALLY]","[Range].[ANUALLY].&[2024]") -> 0.0017297762
A34: JAN | C34: 105400 | G34: =SUM(C34/B34) -> #DIV/0!
A35: FEB | B35: 2010 | C35: 935200 | G35: =SUM(C35/B35) -> 465.27363
A36: MAR | C36: 109290 | G36: =SUM(C36/B36) -> #DIV/0!
A37: APR | C37: 12110 | G37: =SUM(C37/B37) -> #DIV/0!
A38: 2025 | B38: 6141 | C38: 3357300 | G38: =SUM(C38/B38) -> 546.70249 | L38: =GETPIVOTDATA("[Measures].[Sum of Total Qty Produced]",$A$5,"[Range].[ANUALLY]","[Range].[ANUALLY].&[2025]")/GETPIVOTDATA("[Measures].[Sum of Total Cost]",$A$5,"[Range].[ANUALLY]","[Range].[ANUALLY].&[2025]") -> 0.0018291484
A39: MAY | B39: 1526 | C39: 814450 | G39: =SUM(C39/B39) -> 533.7156
A40: JUN | C40: 69375 | G40: =SUM(C40/B40) -> #DIV/0!
A41: JUL | B41: 1656 | C41: 741250 | G41: =SUM(C41/B41) -> 447.61473
A42: AUG | C42: 23550 | G42: =SUM(C42/B42) -> #DIV/0!
A43: SEP | C43: 141250 | G43: =SUM(C43/B43) -> #DIV/0!
A44: OCT | B44: 584 | C44: 273450 | G44: =SUM(C44/B44) -> 468.2363
A45: NOV | B45: 2375 | C45: 1235025 | G45: =SUM(C45/B45) -> 520.01053
A46: DEC | C46: 58950 | G46: =SUM(C46/B46) -> #DIV/0!
A47: Grand Total | B47: 45879 | C47: 15454975 | G47: =SUM(C47/B47) -> 336.86382

Sheet COST BREAKDOWN OVER TIME
A3: Row Labels | B3: Sum of Total Cost | C3: Sum of Sand Cost | D3: Sum of Cement Cost | E3: Sum of Operators' Payment | F3: Sum of Fuel Cost | G3: Sum of Maintenance | H3: Sum of Delivery Cost
A4: 2021 | B4: 276125 | C4: 90000 | D4: 140000 | E4: 42000 | F4: 4125
A5: 44531 | B5: 276125 | C5: 90000 | D5: 140000 | E5: 42000 | F5: 4125
A6: 2022 | B6: 5092800 | C6: 1857500 | D6: 1608150 | E6: 568400 | F6: 53400 | G6: 90400 | H6: 914950
A7: 44562 | B7: 63700 | H7: 63700
A8: 44593 | B8: 472150 | C8: 147500 | D8: 189000 | E8: 67500 | F8: 4000 | H8: 64150
A9: 44621 | B9: 255900 | C9: 70000 | D9: 119400 | E9: 22400 | F9: 4000 | H9: 40100
A10: 44652 | B10: 340400 | C10: 120000 | D10: 90000 | E10: 48000 | F10: 4400 | H10: 78000
A11: 44682 | B11: 115800 | C11: 40000 | D11: 40000 | E11: 15000 | F11: 2000 | H11: 18800
A12: 44713 | B12: 261800 | C12: 120000 | D12: 82000 | E12: 22500 | F12: 2000 | H12: 35300
A13: 44743 | B13: 142700 | C13: 50000 | D13: 45700 | E13: 15000 | F13: 2000 | H13: 30000
A14: 44774 | B14: 1295200 | C14: 500000 | D14: 348300 | E14: 129000 | F14: 10000 | G14: 77900 | H14: 230000
A15: 44805 | B15: 444350 | C15: 100000 | D15: 214650 | E15: 72000 | F15: 8000 | G15: 2000 | H15: 47700
A16: 44835 | B16: 1017500 | C16: 435000 | D16: 283500 | E16: 112500 | F16: 8000 | G16: 5500 | H16: 173000
A17: 44866 | B17: 172000 | C17: 50000 | D17: 40500 | E17: 15000 | F17: 4000 | G17: 5000 | H17: 57500
A18: 44896 | B18: 511300 | C18: 225000 | D18: 155100 | E18: 49500 | F18: 5000 | H18: 76700
A19: 2023 | B19: 5566750 | C19: 2147500 | D19: 1816750 | E19: 616300 | F19: 86180 | G19: 52700 | H19: 847320
A20: 44927 | B20: 258900 | C20: 87500 | D20: 86400 | E20: 24000 | F20: 4000 | H20: 57000
A21: 44958
A22: 44986 | B22: 568960 | C22: 187500 | D22: 209000 | E22: 66000 | F22: 7500 | G22: 2000 | H22: 96960
A23: 45017 | B23: 877290 | C23: 362500 | D23: 328900 | E23: 120000 | F23: 11030 | G23: 2000 | H23: 52860
A24: 45047 | B24: 179420 | C24: 37500 | D24: 32900 | E24: 9000 | F24: 1500 | H24: 98520
A25: 45078 | B25: 442200 | C25: 212500 | D25: 145500 | E25: 30000 | F25: 2000 | H25: 52200
A26: 45108 | B26: 360670 | C26: 137500 | D26: 135300 | E26: 32000 | F26: 7470 | G26: 20200 | H26: 28200
A27: 45139 | B27: 275580 | C27: 125000 | D27: 87200 | E27: 33500 | F27: 3480 | H27: 26400
A28: 45170 | B28: 690830 | C28: 237500 | D28: 230050 | E28: 74800 | F28: 12800 | G28: 20000 | H28: 115680
A29: 45200 | B29: 971030 | C29: 360000 | D29: 283550 | E29: 138600 | F29: 15600 | G29: 3000 | H29: 170280
A30: 45231 | B30: 295620 | C30: 100000 | D30: 98100 | E30: 32300 | F30: 4800 | G30: 1500 | H30: 58920
A31: 45261 | B31: 646250 | C31: 300000 | D31: 179850 | E31: 56100 | F31: 16000 | G31: 4000 | H31: 90300
A32: 2024 | B32: 1162000 | C32: 400000 | D32: 435800 | E32: 78000 | F32: 10000 | G32: 10000 | H32: 229320
A33: 45292 | B33: 105400 | C33: 45000 | G33: 10000 | H33: 50400
A34: 45323 | B34: 935200 | C34: 270000 | D34: 435800 | E34: 78000 | F34: 10000 | H34: 141400
A35: 45352 | B35: 109290 | C35: 85000 | H35: 24290
A36: 45383 | B36: 12110 | H36: 12110
A37: 45413
A38: 45444 | H38: 1120
A39: 45474
A40: 45505
A41: 45536
A42: 45566
A43: 45597
A44: 45627
A45: 2025 | B45: 3357300 | C45: 1010000 | D45: 1157100 | E45: 351000 | F45: 84750 | G45: 381700 | H45: 372750
A46: 45658
A47: 45689
A48: 45717
A49: 45748
A50: 45778 | B50: 814450 | C50: 100000 | D50: 367500 | E50: 87000 | F50: 22250 | G50: 237700
A51: 45809 | B51: 69375 | H51: 69375
A52: 45839 | B52: 741250 | C52: 300000 | D52: 265500 | E52: 92000 | F52: 20000 | H52: 63750
A53: 45870 | B53: 23550 | H53: 23550
A54: 45901 | B54: 141250 | C54: 100000 | H54: 41250
A55: 45931 | B55: 273450 | D55: 122400 | E55: 30000 | F55: 10000 | G55: 80000 | H55: 31050
A56: 45962 | B56: 1235025 | C56: 510000 | D56: 401700 | E56: 142000 | F56: 32500 | G56: 64000 | H56: 84825
A57: 45992 | B57: 58950 | H57: 58950
A58: Grand Total | B58: 15454975 | C58: 5505000 | D58: 5157800 | E58: 1655700 | F58: 238455 | G58: 534800 | H58: 2364340
A59: Grand Total% (Major Cost_Driver) | B59: =SUM(C59:H59) -> 1.0000725 | C59: =C58/B58 -> 0.35619598 | D59: =D58/B58 -> 0.33373072 | E59: =E58/B58 -> 0.10713055 | F59: =F58/B58 -> 0.015429012 | G59: =G58/B58 -> 0.034603744 | H59: =H58/B58 -> 0.15298245
A61: Year of Production | B61: Total Cost % | C61: Sand Cost % | D61: Cement Cost % | E61: Operator Cost % | F61: Fuel Cost % | G61: Maintenance Cost % | H61: Delivery Cost %
A62: 2021 | B62: =SUM(C62:H62) -> 1 | C62: =GETPIVOTDATA("Sum of Sand Cost",$A$3,"ANUALLY",2021)/GETPIVOTDATA("Sum of Total Cost",$A$3,"ANUALLY",2021) -> 0.32593934 | D62: =GETPIVOTDATA("Sum of Cement Cost",$A$3,"ANUALLY",2021)/GETPIVOTDATA("Sum of Total Cost",$A$3,"ANUALLY",2021) -> 0.50701675 | E62: =GETPIVOTDATA("Sum of Operators' Payment",$A$3,"ANUALLY",2021)/GETPIVOTDATA("Sum of Total Cost",$A$3,"ANUALLY",2021) -> 0.15210502 | F62: =GETPIVOTDATA("Sum of Fuel Cost",$A$3,"ANUALLY",2021)/GETPIVOTDATA("Sum of Total Cost",$A$3,"ANUALLY",2021) -> 0.014938886
A63: 2022 | B63: =SUM(C63:H63) -> 1 | C63: =GETPIVOTDATA("Sum of Sand Cost",$A$3,"ANUALLY",2022)/GETPIVOTDATA("Sum of Total Cost",$A$3,"ANUALLY",2022) -> 0.3647306 | D63: =GETPIVOTDATA("Sum of Cement Cost",$A$3,"ANUALLY",2022)/GETPIVOTDATA("Sum of Total Cost",$A$3,"ANUALLY",2022) -> 0.31576932 | E63: =GETPIVOTDATA("Sum of Operators' Payment",$A$3,"ANUALLY",2022)/GETPIVOTDATA("Sum of Total Cost",$A$3,"ANUALLY",2022) -> 0.11160855 | F63: =GETPIVOTDATA("Sum of Fuel Cost",$A$3,"ANUALLY",2022)/GETPIVOTDATA("Sum of Total Cost",$A$3,"ANUALLY",2022) -> 0.010485391 | G63: =GETPIVOTDATA("Sum of Maintenance",$A$3,"ANUALLY",2022)/GETPIVOTDATA("Sum of Total Cost",$A$3,"ANUALLY",2022) -> 0.01775055 | H63: =GETPIVOTDATA("Sum of Delivery Cost",$A$3,"ANUALLY",2022)/GETPIVOTDATA("Sum of Total Cost",$A$3,"ANUALLY",2022) -> 0.17965559
A64: 2023 | B64: =SUM(C64:H64) -> 1 | C64: =GETPIVOTDATA("Sum of Sand Cost",$A$3,"ANUALLY",2023)/GETPIVOTDATA("Sum of Total Cost",$A$3,"ANUALLY",2023) -> 0.38577267 | D64: =GETPIVOTDATA("Sum of Cement Cost",$A$3,"ANUALLY",2023)/GETPIVOTDATA("Sum of Total Cost",$A$3,"ANUALLY",2023) -> 0.32635739 | E64: =GETPIVOTDATA("Sum of Operators' Payment",$A$3,"ANUALLY",2023)/GETPIVOTDATA("Sum of Total Cost",$A$3,"ANUALLY",2023) -> 0.11071092 | F64: =GETPIVOTDATA("Sum of Fuel Cost",$A$3,"ANUALLY",2023)/GETPIVOTDATA("Sum of Total Cost",$A$3,"ANUALLY",2023) -> 0.015481205 | G64: =GETPIVOTDATA("Sum of Maintenance",$A$3,"ANUALLY",2023)/GETPIVOTDATA("Sum of Total Cost",$A$3,"ANUALLY",2023) -> 0.0094669241 | H64: =GETPIVOTDATA("Sum of Delivery Cost",$A$3,"ANUALLY",2023)/GETPIVOTDATA("Sum of Total Cost",$A$3,"ANUALLY",2023) -> 0.1522109
A65: 2024 | B65: =SUM(C65:H65) -> 1.0009639 | C65: =GETPIVOTDATA("Sum of Sand Cost",$A$3,"ANUALLY",2024)/GETPIVOTDATA("Sum of Total Cost",$A$3,"ANUALLY",2024) -> 0.34423408 | D65: =GETPIVOTDATA("Sum of Cement Cost",$A$3,"ANUALLY",2024)/GETPIVOTDATA("Sum of Total Cost",$A$3,"ANUALLY",2024) -> 0.37504303 | E65: =GETPIVOTDATA("Sum of Operators' Payment",$A$3,"ANUALLY",2024)/GETPIVOTDATA("Sum of Total Cost",$A$3,"ANUALLY",2024) -> 0.067125645 | F65: =GETPIVOTDATA("Sum of Fuel Cost",$A$3,"ANUALLY",2024)/GETPIVOTDATA("Sum of Total Cost",$A$3,"ANUALLY",2024) -> 0.008605852 | G65: =GETPIVOTDATA("Sum of Maintenance",$A$3,"ANUALLY",2024)/GETPIVOTDATA("Sum of Total Cost",$A$3,"ANUALLY",2024) -> 0.008605852 | H65: =GETPIVOTDATA("Sum of Delivery Cost",$A$3,"ANUALLY",2024)/GETPIVOTDATA("Sum of Total Cost",$A$3,"ANUALLY",2024) -> 0.1973494
A66: 2025 | B66: =SUM(C66:H66) -> 1 | C66: =GETPIVOTDATA("Sum of Sand Cost",$A$3,"ANUALLY",2025)/GETPIVOTDATA("Sum of Total Cost",$A$3,"ANUALLY",2025) -> 0.30083698 | D66: =GETPIVOTDATA("Sum of Cement Cost",$A$3,"ANUALLY",2025)/GETPIVOTDATA("Sum of Total Cost",$A$3,"ANUALLY",2025) -> 0.34465195 | E66: =GETPIVOTDATA("Sum of Operators' Payment",$A$3,"ANUALLY",2025)/GETPIVOTDATA("Sum of Total Cost",$A$3,"ANUALLY",2025) -> 0.1045483 | F66: =GETPIVOTDATA("Sum of Fuel Cost",$A$3,"ANUALLY",2025)/GETPIVOTDATA("Sum of Total Cost",$A$3,"ANUALLY",2025) -> 0.025243499 | G66: =GETPIVOTDATA("Sum of Maintenance",$A$3,"ANUALLY",2025)/GETPIVOTDATA("Sum of Total Cost",$A$3,"ANUALLY",2025) -> 0.11369255 | H66: =GETPIVOTDATA("Sum of Delivery Cost",$A$3,"ANUALLY",2025)/GETPIVOTDATA("Sum of Total Cost",$A$3,"ANUALLY",2025) -> 0.11102672
A67: TOTAL % COST VOLATILITY | C67: =SUM(C62:C66) -> 1.7215137 | D67: =SUM(D62:D66) -> 1.8688384 | E67: =SUM(E62:E66) -> 0.54609843 | F67: =SUM(F62:F66) -> 0.074754834 | G67: =SUM(G62:G66) -> 0.14951588 | H67: =SUM(H62:H66) -> 0.6402426

Sheet INPUT vs OUTPUT EFFICIENCY
A5: Row Labels | B5: Sum of Total Qty Sold | C5: Sum of Total Qty Produced | D5: Sum of Cement Cost | E5: Sum of Operators' Payment | F5: Sum of Bag Produced | G5: Sum of Tons Of Sand | I5: LABOUR PRODUCTIVITY | J5: SAND EFFICIENCY | K5: CEMENT EFFICIENCY | L5: PRODUCTION vs SALES EFFICIENCY = QTY_SOLD / QTY_PRODUCED %
A6: 2021 | C6: 1856 | D6: 140000 | E6: 42000 | F6: 35 | G6: 30 | I6: =GETPIVOTDATA("Sum of Total Qty Produced",$A$5,"ANUALLY",2021)/GETPIVOTDATA("Sum of Operators' Payment",$A$5,"ANUALLY",2021) -> 0.044190476 | J6: =GETPIVOTDATA("Sum of Total Qty Produced",$A$5,"ANUALLY",2021)/GETPIVOTDATA("Sum of Tons Of Sand ",$A$5,"ANUALLY",2021) -> 61.866667 | K6: =GETPIVOTDATA("Sum of Total Qty Produced",$A$5,"ANUALLY",2021)/GETPIVOTDATA("Sum of Bag Produced",$A$5,"ANUALLY",2021) -> 53.028571 | L6: =B6/C6 -> 0
A7: DEC | C7: 1856 | D7: 140000 | E7: 42000 | F7: 35 | G7: 30
A8: 2022 | B8: 18299 | C8: 18559 | D8: 1608150 | E8: 568400 | F8: 385 | G8: 428 | I8: =GETPIVOTDATA("Sum of Total Qty Produced",$A$5,"ANUALLY",2022)/GETPIVOTDATA("Sum of Operators' Payment",$A$5,"ANUALLY",2022) -> 0.032651302 | J8: =GETPIVOTDATA("Sum of Total Qty Produced",$A$5,"ANUALLY",2022)/GETPIVOTDATA("Sum of Tons Of Sand ",$A$5,"ANUALLY",2022) -> 43.36215 | K8: =C8/GETPIVOTDATA("Sum of Bag Produced",$A$5,"ANUALLY",2022) -> 48.205195 | L8: =B8/C8 -> 0.98599062
A9: JAN | B9: 1274
A10: FEB | B10: 1283 | C10: 2360 | D10: 189000 | E10: 67500 | F10: 45 | G10: 48
A11: MAR | B11: 802 | C11: 788 | D11: 119400 | E11: 22400 | F11: 16 | G11: 20
A12: APR | B12: 1560 | C12: 1498 | D12: 90000 | E12: 48000 | F12: 33 | G12: 30
A13: MAY | B13: 376 | C13: 546 | D13: 40000 | E13: 15000 | F13: 11 | G13: 10
A14: JUN | B14: 706 | C14: 645 | D14: 82000 | E14: 22500 | F14: 15 | G14: 30
A15: JUL | B15: 600 | C15: 780 | D15: 45700 | E15: 15000 | F15: 13 | G15: 10
A16: AUG | B16: 4600 | C16: 3795 | D16: 348300 | E16: 129000 | F16: 86 | G16: 100
A17: SEP | B17: 954 | C17: 2286 | D17: 214650 | E17: 72000 | F17: 48 | G17: 20
A18: OCT | B18: 3460 | C18: 3774 | D18: 283500 | E18: 112500 | F18: 75 | G18: 90
A19: NOV | B19: 1150 | C19: 430 | D19: 40500 | E19: 15000 | F19: 10 | G19: 10
A20: DEC | B20: 1534 | C20: 1657 | D20: 155100 | E20: 49500 | F20: 33 | G20: 60
A21: 2023 | B21: 16622 | C21: 17313 | D21: 1816750 | E21: 616300 | F21: 346 | G21: 412 | I21: =GETPIVOTDATA("Sum of Total Qty Produced",$A$5,"ANUALLY",2023)/GETPIVOTDATA("Sum of Operators' Payment",$A$5,"ANUALLY",2023) -> 0.028091838 | J21: =GETPIVOTDATA("Sum of Total Qty Produced",$A$5,"ANUALLY",2023)/GETPIVOTDATA("Sum of Tons Of Sand ",$A$5,"ANUALLY",2023) -> 42.021845 | K21: =C21/F21 -> 50.037572 | L21: =B21/C21 -> 0.9600878
A22: JAN | B22: 950 | C22: 824 | D22: 86400 | E22: 24000 | F22: 16 | G22: 18
A23: MAR | B23: 1616 | C23: 2011 | D23: 209000 | E23: 66000 | F23: 44 | G23: 38
A24: APR | B24: 3381 | C24: 3615 | D24: 328900 | E24: 120000 | F24: 70 | G24: 72
A25: MAY | B25: 1642 | C25: 504 | D25: 32900 | E25: 9000 | F25: 6 | G25: 8
A26: JUN | B26: 870 | C26: 760 | D26: 145500 | E26: 30000 | F26: 20 | G26: 42
A27: JUL | B27: 470 | C27: 903 | D27: 135300 | E27: 32000 | F27: 21 | G27: 28
A28: AUG | B28: 440 | C28: 1040 | D28: 87200 | E28: 33500 | F28: 21 | G28: 25
A29: SEP | B29: 1928 | C29: 2079 | D29: 230050 | E29: 74800 | F29: 44 | G29: 48
A30: OCT | B30: 2838 | C30: 2780 | D30: 283550 | E30: 138600 | F30: 52 | G30: 65
A31: NOV | B31: 982 | C31: 1140 | D31: 98100 | E31: 32300 | F31: 19 | G31: 18
A32: DEC | B32: 1505 | C32: 1657 | D32: 179850 | E32: 56100 | F32: 33 | G32: 50
A33: 2024 | B33: 3260 | C33: 2010 | D33: 435800 | E33: 78000 | F33: 40 | G33: 63 | I33: =GETPIVOTDATA("Sum of Total Qty Produced",$A$5,"ANUALLY",2024)/GETPIVOTDATA("Sum of Operators' Payment",$A$5,"ANUALLY",2024) -> 0.025769231 | J33: =GETPIVOTDATA("Sum of Total Qty Produced",$A$5,"ANUALLY",2024)/GETPIVOTDATA("Sum of Tons Of Sand ",$A$5,"ANUALLY",2024) -> 31.904762 | K33: =C33/F33 -> 50.25 | L33: =B33/C33 -> 1.6218905
A34: JAN | B34: 720 | G34: 8
A35: FEB | B35: 2020 | C35: 2010 | D35: 435800 | E35: 78000 | F35: 40 | G35: 45
A36: MAR | B36: 347 | G36: 10
A37: APR | B37: 173
A38: 2025 | B38: 5033 | C38: 6141 | D38: 1157100 | E38: 351000 | F38: 110 | G38: 110 | I38: =GETPIVOTDATA("Sum of Total Qty Produced",$A$5,"ANUALLY",2025)/GETPIVOTDATA("Sum of Operators' Payment",$A$5,"ANUALLY",2025) -> 0.017495726 | J38: =GETPIVOTDATA("Sum of Total Qty Produced",$A$5,"ANUALLY",2025)/GETPIVOTDATA("Sum of Tons Of Sand ",$A$5,"ANUALLY",2025) -> 55.827273 | K38: =C38/F38 -> 55.827273 | L38: =B38/C38 -> 0.81957336
A39: MAY | C39: 1526 | D39: 367500 | E39: 87000 | F39: 29 | G39: 10
A40: JUN | B40: 925
A41: JUL | B41: 850 | C41: 1656 | D41: 265500 | E41: 92000 | F41: 29 | G41: 30
A42: AUG | B42: 377
A43: SEP | B43: 550 | G43: 10
A44: OCT | B44: 414 | C44: 584 | D44: 122400 | E44: 30000 | F44: 10
A45: NOV | B45: 1131 | C45: 2375 | D45: 401700 | E45: 142000 | F45: 42 | G45: 60
A46: DEC | B46: 786
A47: Grand Total | B47: 43214 | C47: 45879 | D47: 5157800 | E47: 1655700 | F47: 916 | G47: 1043
B52: LABOUR COST per BAG = TOTAL OPERATORS' PAYMENT / TOTAL_QTY of BAGS_PRODUCED
B54: LABOUR PRODUCTIVITY = QTY_PRODUCED / OPERATORS' PAYMENT
B56: MATERIAL EFFICIENCY= QTY_PRODUCED / BAG PRODUCED
B58: PRODUCTION vs SALES EFFICIENCY = QTY_SOLD / QTY_PRODUCED %
B60: WASTAGE RATIO = DAMAGE_QTY / QTY_PRODUCED %
B62: UNSOLD RATIO = (QTY_PRODUCED - QTY_SOLD) / QTY_PRODUCED %

Sheet TIME OF SALES
A1: Product Type | B1: (All)
A3: Sum of Qty Sold | B3: Column Labels
A4: Row Labels | B4: MONDAY | C4: TUESDAY | D4: WEDNESDAY | E4: THURSDAY | F4: FRIDAY | G4: SATURDAY | H4: SUNDAY | I4: Grand Total
A5: 2022 | B5: 2186 | C5: 2065 | D5: 1679 | E5: 3672 | F5: 7260 | G5: 1302 | H5: 135 | I5: 18299
A6: JANUARY | B6: 500 | D6: 300 | G6: 474 | I6: 1274
A7: FEBRUARY | B7: 12 | C7: 575 | D7: 400 | E7: 130 | F7: 150 | G7: 16 | I7: 1283
A8: MARCH | B8: 200 | E8: 2 | F8: 500 | G8: 100 | I8: 802
A9: APRIL | E9: 1200 | F9: 200 | G9: 160 | I9: 1560
A10: MAY | B10: 266 | C10: 50 | E10: 60 | I10: 376
A11: JUNE | B11: 80 | C11: 40 | E11: 150 | F11: 400 | G11: 36 | I11: 706
A12: JULY | D12: 100 | G12: 500 | I12: 600
A13: AUGUST | F13: 4600 | I13: 4600
A14: SEPTEMBER | B14: 278 | C14: 50 | D14: 510 | F14: 100 | G14: 16 | I14: 954
A15: OCTOBER | B15: 600 | C15: 1000 | E15: 1280 | F15: 580 | I15: 3460
A16: NOVEMBER | B16: 150 | C16: 250 | D16: 150 | E16: 600 | I16: 1150
A17: DECEMBER | B17: 100 | C17: 100 | D17: 219 | E17: 250 | F17: 730 | H17: 135 | I17: 1534
A18: 2023 | B18: 2882 | C18: 3185 | D18: 5563 | E18: 2043 | F18: 1459 | G18: 1400 | H18: 90 | I18: 16622
A19: JANUARY | B19: 100 | C19: 400 | D19: 400 | E19: 16 | F19: 34 | I19: 950
A20: MARCH | B20: 1016 | D20: 15 | E20: 360 | F20: 225 | I20: 1616
A21: APRIL | B21: 40 | C21: 600 | D21: 2516 | G21: 225 | I21: 3381
A22: MAY | B22: 50 | C22: 715 | D22: 877 | I22: 1642
A23: JUNE | B23: 200 | D23: 100 | E23: 430 | G23: 130 | H23: 10 | I23: 870
A24: JULY | B24: 70 | F24: 200 | G24: 200 | I24: 470
A25: AUGUST | B25: 180 | E25: 180 | H25: 80 | I25: 440
A26: SEPTEMBER | B26: 800 | C26: 320 | F26: 800 | G26: 8 | I26: 1928
A27: OCTOBER | B27: 376 | C27: 900 | D27: 950 | E27: 175 | G27: 437 | I27: 2838
A28: NOVEMBER | B28: 50 | C28: 250 | D28: 100 | E28: 332 | G28: 250 | I28: 982
A29: DECEMBER | D29: 605 | E29: 550 | F29: 200 | G29: 150 | I29: 1505
A30: 2024 | B30: 176 | C30: 350 | D30: 100 | E30: 962 | F30: 1085 | G30: 603 | I30: 3276
A31: JANUARY | B31: 100 | C31: 20 | D31: 100 | E31: 500 | I31: 720
A32: FEBRUARY | B32: 20 | C32: 50 | E32: 450 | F32: 1000 | G32: 500 | I32: 2020
A33: MARCH | C33: 250 | E33: 12 | F33: 85 | I33: 347
A34: APRIL | B34: 40 | C34: 30 | G34: 103 | I34: 173
A35: JUNE | B35: 16 | I35: 16
A36: 2025 | B36: 645 | C36: 266 | D36: 877 | E36: 900 | F36: 529 | G36: 1776 | H36: 40 | I36: 5033
A37: JUNE | B37: 625 | E37: 300 | I37: 925
A38: JULY | E38: 200 | G38: 650 | I38: 850
A39: AUGUST | D39: 38 | E39: 250 | F39: 24 | G39: 25 | H39: 40 | I39: 377
A40: SEPTEMBER | D40: 500 | F40: 50 | I40: 550
A41: OCTOBER | C41: 230 | D41: 14 | E41: 150 | F41: 20 | I41: 414
A42: NOVEMBER | F42: 30 | G42: 1101 | I42: 1131
A43: DECEMBER | B43: 20 | C43: 36 | D43: 325 | F43: 405 | I43: 786
A44: Grand Total | B44: 5889 | C44: 5866 | D44: 8219 | E44: 7577 | F44: 10333 | G44: 5081 | H44: 265 | I44: 43230

Sheet RATE PER BLOCK TYPES OVERTIME
A1: Product Type | B1: 9 Inches
A3: Row Labels | B3: Average of Rate | F3: YEAR-ON-YEAR GROWTH (YOY) = (CURRENT YEAR - PREVIOUS YEAR) / PREVIOSE YEAR %
A4: 2022 | B4: 360.2381 | F4: 0
A5: JANUARY | B5: 295
A6: FEBRUARY | B6: 300
A7: APRIL | B7: 370
A8: JUNE | B8: 320
A9: AUGUST | B9: 350
A10: SEPTEMBER | B10: 350
A11: OCTOBER | B11: 378.33333
A12: NOVEMBER | B12: 390
A13: DECEMBER | B13: 386.66667
A14: 2023 | B14: 422.79412
A15: JANUARY | B15: 378.33333
A16: MARCH | B16: 402.5
A17: APRIL | B17: 400 | F17: =(GETPIVOTDATA("Rate ",$A$3,"ANUALLY",2023)-GETPIVOTDATA("Rate ",$A$3,"ANUALLY",2022))/GETPIVOTDATA("Rate ",$A$3,"ANUALLY",2022) -> 0.17365188
A18: MAY | B18: 350
A19: JUNE | B19: 390
A20: JULY | B20: 415
A21: AUGUST | B21: 450
A22: SEPTEMBER | B22: 447.5
A23: OCTOBER | B23: 453.33333
A24: NOVEMBER | B24: 500
A25: DECEMBER | B25: 492
A26: 2024 | B26: 645
A27: FEBRUARY | B27: 590
A28: APRIL | B28: 700
A29: JUNE | B29: 700 | F29: =(GETPIVOTDATA("Rate ",$A$3,"ANUALLY",2024)-GETPIVOTDATA("Rate ",$A$3,"ANUALLY",2023))/GETPIVOTDATA("Rate ",$A$3,"ANUALLY",2023) -> 0.52556522
A30: 2025 | B30: 955.55556
A31: JUNE | B31: 1000
A32: JULY | B32: 950
A33: AUGUST | B33: 925
A34: OCTOBER | B34: 975
A35: NOVEMBER | B35: 1000 | F35: =(GETPIVOTDATA("Rate ",$A$3,"ANUALLY",2025)-GETPIVOTDATA("Rate ",$A$3,"ANUALLY",2024))/GETPIVOTDATA("Rate ",$A$3,"ANUALLY",2024) -> 0.48148148
A36: DECEMBER | B36: 925
A37: Grand Total | B37: 487.05882

Sheet CUSTOMER VALUE ANALYSIS 
A1: Product Type | B1: (All)
A3: Row Labels | B3: Sum of Qty Sold | C3: Sum of Rate | D3: Sum of Revenue
A4: ADEBISI SCH. | B4: 200 | C4: 600 | D4: 60000
A5: AHLU SUNNAH | B5: 14 | C5: 800 | D5: 6200
A6: ALHAJA CSTM RFRL 1 | B6: 255 | C6: 1200 | D6: 107500
A7: ALHAJA CSTM RFRL 2 | B7: 40 | C7: 350 | D7: 14000
A8: ALHJ ONAARA | B8: 160 | C8: 730 | D8: 59800
A9: ARISE CSTM | B9: 700 | C9: 340 | D9: 238000
A10: AYO CSTM | B10: 30 | C10: 390 | D10: 11500
A11: BABA ADINI | B11: 16 | C11: 700 | D11: 11200
A12: BABA ASOLO | B12: 792 | C12: 1080 | D12: 283200
A13: BABA IBEJI BRICK-LAYER | B13: 155 | C13: 550 | D13: 45250
A14: BABA OLOKO CSTM | B14: 1050 | C14: 3100 | D14: 727500
A15: BABA SAMSON | B15: 500 | C15: 940 | D15: 145000
... A90: Grand Total | B90: 43167 | C90: 90812 | D90: 18633540

Sheet CUSTOMER CREDIT RISK 
A1: Product Type | B1: (All)
A3: Row Labels | B3: Sum of Amount | C3: Sum of Bad Debt | D3: Sum of Revenue
A4: ADEBISI SCH. | B4: 60000 | D4: 60000
A5: AHLU SUNNAH | B5: 11200 | C5: 5000 | D5: 6200
A6: ALHAJA CSTM RFRL 1 | B6: 108500 | C6: 1000 | D6: 107500
A7: ALHAJA CSTM RFRL 2 | B7: 14000 | D7: 14000
A8: ALHJ ONAARA | B8: 59800 | D8: 59800
A9: ARISE CSTM | B9: 238000 | D9: 238000 | H9: ESTIMATED BAD DEBT RATIO =BAD_DEBT/REVENUE %
A10: Arrangement falling | B10: 20000 | C10: 20000 | D10: 0
A11: AYO CSTM | B11: 11700 | C11: 200 | D11: 11500
A12: BABA ADINI | B12: 11200 | D12: 11200
A13: BABA ASOLO | B13: 283200 | D13: 283200
A14: BABA IBEJI BRICK-LAYER | B14: 45250 | D14: 45250
A15: BABA OLOKO CSTM | B15: 727500 | D15: 727500
A16: BABA SAMSON | B16: 145000 | D16: 145000
A17: BISHOP BRICKLAYER | B17: 221500 | D17: 221500
A18: BRICKLAYER CONERPICE 2 | B18: 2800 | D18: 2800
A19: BRICKLAYER CONERPIEC 1 | B19: 5280 | D19: 5280
A20: BRICKLAYER D.P.R.3 | B20: 240000 | D20: 240000
A21: BRICKLAYER SURVEYOR | B21: 11180 | D21: 11180
A22: BRICKLAYER TELLA | B22: 31500 | D22: 31500
A23: CAPENTER CSTM | B23: 480000 | D23: 480000
... A43: CSTM. WILLY | B43: 143500 | D43: 143500
A44: CSTM@OKO-OPE | B44: 449000 | C44: 6000 | D44: 443000
A45: D.P.R.3 BRICKLAYER | B45: 24600 | C45: 100 | D45: 24500
A46: DAD EMA WELDER CSTM | B46: 74000 | D46: 74000
A47: DAD PRAISE | B47: 60000 | C47: 40000 | D47: 20000
A48: DAD PRAISE REFERRAL 1 | B48: 73300 | C48: 700 | D48: 72600
A49: DAD PRAISE REFERRAL 3 | B49: 751900 | D49: 751900
A50: DAD PRAISE REFERRAL 4 | B50: 154000 | D50: 154000
A51: DAD SALAM BRICKLAYER | B51: 12000 | D51: 12000
A52: DAD SEMILORE | B52: 56000 | D52: 56000
A53: EGBON BIOYE | B53: 150000 | D53: 150000
A54: ELECT. AFEEZ | B54: 489500 | D54: 489500
A55: ENG. LEKAN/BABA | B55: 91200 | D55: 91200
A56: ENG. TUNDE | B56: 237500 | D56: 237500
A57: ENG. WAHEED | B57: 2439100 | C57: 17500 | D57: 2421600
A58: ENG. WAHEED PLUMBER | B58: 522500 | D58: 522500
A59: GBAJUE CSTM | B59: 7030 | C59: 30 | D59: 7000
A60: IJIKU POULTRY CSTM | B60: 140000 | D60: 140000
A61: IYA ADURA | B61: 39000 | D61: 39000
A62: IYA IZOBO REFERRAL 1 | B62: 105000 | D62: 105000
A63: IYA SODIQ | B63: 5250 | D63: 5250
A64: JAWA CSTM | B64: 20000 | D64: 20000
A65: MAMA DAADA | B65: 14400 | D65: 14400
A66: MOSHOOD JOSEPH | B66: 39240 | D66: 39240
A67: MR ADEBAYO/NICE CSTM | B67: 688000 | D67: 688000
A68: MR FLORENCE | B68: 240000 | D68: 240000
A69: MR JEREMIAH | B69: 137440 | D69: 137440
A70: MR LUKMAN NEIGHBOUR | B70: 51000 | D70: 51000
A71: MR&MRS ESUPOFO | B71: 356000 | D71: 356000
A72: MR&MRS OMOLERE | B72: 1469450 | C72: 50250 | D72: 1419200
A73: MR. OLA CSTM | B73: 100000 | D73: 100000
A74: Nearby CSTM@OKO-OPE | B74: 3240 | C74: 140 | D74: 3100
A75: NEIGHBOR OLUWATOYIN | B75: 405000 | D75: 405000
A76: NEIGHBOUR EZEKIEL | B76: 1301500 | D76: 1301500
A77: NEPA CSTM | B77: 157500 | D77: 157500
A78: OBALOLUWA BLOCK | B78: 36000 | D78: 36000
A79: OFFISER HASSAN | B79: 34560 | D79: 34560
A80: OGA SANMI | B80: 128000 | D80: 128000
A81: OLORI | B81: 4800 | C81: 4300 | D81: 500
A82: ORIYOMI | B82: 206250 | D82: 206250
A83: PAAPA | B83: 20000 | D83: 20000
A84: SAMBEST REFERRAL 1 | B84: 73500 | C84: 2150 | D84: 71350
A85: SERIKI | B85: 1000 | D85: 1000
A86: SUPRISE MUMMY | B86: 4800 | D86: 4800
A87: SUPRISE MUMMY FRIEND | B87: 6080 | D87: 6080
A88: SURVEYOR CSTM | B88: 8750 | D88: 8750
A89: SURVEYOR SAMBEST | B89: 294500 | C89: 8000 | D89: 286500 | G89: DEBT RATE =BAD DEBT/TOTAL AMOUNT
A90: THIEVES | B90: 30400 | C90: 30400 | D90: 0
A91: DAD PRAISE REFERRAL 2 | B91: 228000 | D91: 228000
A92: Grand Total | B92: 18819310 | C92: 185770 | D92: 18633540

Sheet PROFIT ANALYSIS OVER TIME 
A3: Row Labels | B3: Sum of 6 Inches Qty | C3: Sum of 7 Inches Qty | D3: Sum of 9 Inches Qty | E3: Sum of Total Qty Produced | F3: Sum of Total Revenue | G3: Sum of Total Cost | H3: Sum of Total Profit | J3: Cost vs Profit Relationship
A4: 2021 | B4: 1020 | C4: 500 | D4: 336 | E4: 1856 | G4: 276125 | H4: -276125 | J4: =GETPIVOTDATA("Sum of Total Profit",$A$3,"ANUALLY",2021)/GETPIVOTDATA("Sum of Total Cost",$A$3,"ANUALLY",2021) -> -1
A5: 44531 | B5: 1020 | C5: 500 | D5: 336 | E5: 1856 | G5: 276125 | H5: -276125
A6: 2022 | B6: 6589 | C6: 3442 | D6: 8528 | E6: 18559 | F6: 6068380 | G6: 5092800 | H6: 975580 | J6: =GETPIVOTDATA("Sum of Total Profit",$A$3,"ANUALLY",2022)/GETPIVOTDATA("Sum of Total Cost",$A$3,"ANUALLY",2022) -> 0.19156063
A7: 44562 | F7: 340250 | G7: 63700 | H7: 276550
A8: 44593 | B8: 900 | C8: 1250 | D8: 210 | E8: 2360 | F8: 347950 | G8: 472150 | H8: -124200
A9: 44621 | B9: 440 | C9: 96 | D9: 252 | E9: 788 | F9: 257600 | G9: 255900 | H9: 1700
A10: 44652 | C10: 700 | D10: 798 | E10: 1498 | F10: 521800 | G10: 340400 | H10: 181400
A11: 44682 | C11: 546 | E11: 546 | F11: 114700 | G11: 115800 | H11: -1100
A12: 44713 | D12: 645 | E12: 645 | F12: 222800 | G12: 261800 | H12: -39000
A13: 44743 | B13: 780 | E13: 780 | F13: 190000 | G13: 142700 | H13: 47300
A14: 44774 | B14: 569 | D14: 3226 | E14: 3795 | F14: 1594000 | G14: 1295200 | H14: 298800
A15: 44805 | B15: 1320 | C15: 450 | D15: 516 | E15: 2286 | F15: 297980 | G15: 444350 | H15: -146370
A16: 44835 | B16: 1740 | C16: 400 | D16: 1634 | E16: 3774 | F16: 1176300 | G16: 1017500 | H16: 158800
A17: 44866 | D17: 430 | E17: 430 | F17: 425000 | G17: 172000 | H17: 253000
A18: 44896 | B18: 840 | D18: 817 | E18: 1657 | F18: 580000 | G18: 511300 | H18: 68700
A19: 2023 | B19: 7143 | C19: 2701 | D19: 7469 | E19: 17313 | F19: 6556450 | G19: 5566750 | H19: 989700 | J19: =GETPIVOTDATA("Sum of Total Profit",$A$3,"ANUALLY",2023)/GETPIVOTDATA("Sum of Total Cost",$A$3,"ANUALLY",2023) -> 0.17778776
A20: 44927 | B20: 480 | D20: 344 | E20: 824 | F20: 351320 | G20: 258900 | H20: 92420
A21: 44958
A22: 44986 | B22: 420 | D22: 1591 | E22: 2011 | F22: 644100 | G22: 568960 | H22: 75140
A23: 45017 | B23: 900 | C23: 2500 | D23: 215 | E23: 3615 | F23: 1015940 | G23: 877290 | H23: 138650
A24: 45047 | B24: 303 | C24: 201 | E24: 504 | F24: 584200 | G24: 179420 | H24: 404780
A25: 45078 | D25: 760 | E25: 760 | F25: 343200 | G25: 442200 | H25: -99000
A26: 45108 | D26: 903 | E26: 903 | F26: 181500 | G26: 360670 | H26: -179170
A27: 45139 | B27: 480 | D27: 560 | E27: 1040 | F27: 182200 | G27: 275580 | H27: -93380
A28: 45170 | B28: 660 | D28: 1419 | E28: 2079 | F28: 841200 | G28: 690830 | H28: 150370
A29: 45200 | B29: 1920 | D29: 860 | E29: 2780 | F29: 1255440 | G29: 971030 | H29: 284410
A30: 45231 | B30: 1140 | E30: 1140 | F30: 446900 | G30: 295620 | H30: 151280
A31: 45261 | B31: 840 | D31: 817 | E31: 1657 | F31: 710450 | G31: 646250 | H31: 64200
A32: 2024 | B32: 1560 | C32: 20 | D32: 430 | E32: 2010 | F32: 1790610 | G32: 1162000 | H32: 628610 | J32: =GETPIVOTDATA("Sum of Total Profit",$A$3,"ANUALLY",2024)/GETPIVOTDATA("Sum of Total Cost",$A$3,"ANUALLY",2024) -> 0.54097246
A33: 45292 | F33: 294000 | G33: 105400 | H33: 188600
A34: 45323 | B34: 1560 | C34: 20 | D34: 430 | E34: 2010 | F34: 1120000 | G34: 935200 | H34: 184800
A35: 45352 | F35: 236350 | G35: 109290 | H35: 127060
A36: 45383 | F36: 129060 | G36: 12110 | H36: 116950
A37: 45413
A38: 45444 | F38: 11200 | H38: 11200
A39: 45474
A40: 45505
A41: 45536
A42: 45566
A43: 45597
A44: 45627
A45: 2025 | B45: 4286 | D45: 1855 | E45: 6141 | F45: 4218100 | G45: 3357300 | H45: 860800 | J45: =GETPIVOTDATA("Sum of Total Profit",$A$3,"ANUALLY",2025)/GETPIVOTDATA("Sum of Total Cost",$A$3,"ANUALLY",2025) -> 0.25639651
A46: 45658
A47: 45689
A48: 45717
A49: 45748
A50: 45778 | B50: 960 | D50: 566 | E50: 1526 | G50: 814450 | H50: -814450
A51: 45809 | F51: 760000 | G51: 69375 | H51: 690625
A52: 45839 | B52: 1184 | D52: 472 | E52: 1656 | F52: 762500 | G52: 741250 | H52: 21250
A53: 45870 | F53: 290300 | G53: 23550 | H53: 266750
A54: 45901 | F54: 436500 | G54: 141250 | H54: 295250
A55: 45931 | B55: 584 | E55: 584 | F55: 359700 | G55: 273450 | H55: 86250
A56: 45962 | B56: 1558 | D56: 817 | E56: 2375 | F56: 885500 | G56: 1235025 | H56: -349525
A57: 45992 | F57: 723600 | G57: 58950 | H57: 664650
A58: Grand Total | B58: 20598 | C58: 6663 | D58: 18618 | E58: 45879 | F58: 18633540 | G58: 15454975 | H58: 3178565 | J58: =GETPIVOTDATA("Sum of Total Profit",$A$3)/GETPIVOTDATA("Sum of Total Cost",$A$3) -> 0.20566614
A60: 1 | B60: Cost vs Profit Relationship = PROFIT / COST %
A61: 2 | B61: PROFIT MARGIN ="PROFIT/REVENUE" or "REVENUE-TOTAL COST/REVENUE %"
A62: 3 | B62: BLOCK TYPE (6, 7 & 9) PROFIT per BAG = "SALES PER BAG - COSTS PER BAG" or "% WORTH OF BLOCK QTY * UNIT PROFIT PER BAG"
B64: METRICS | C64: 6 Inches Qty Sold/Bag | D64: 7 Inches Qty Sold/Bag | E64: 9 Inches Qty Sold/Bag | F64: Total | G64: HINTS
B65: Block Type per Total Bags | C65: =18485/60 -> 308.08333 | D65: =6620/50 -> 132.4 | E65: =18125/43 -> 421.51163 | F65: =SUM(C65:E65) -> 861.99496 | G65: Total Qty Sold/Block Qty
B66: % T-Bag units | C66: =C65/F65 -> 0.35740735 | D66: =D65/F65 -> 0.15359719 | E66: =E65/F65 -> 0.48899547 | F66: =SUM(C66:E66) -> 1 | G66: Block Type Bags /Total %
B67: % worth on T-Profit | C67: =C66*GETPIVOTDATA("Sum of Total Profit",$A$3) -> 1136042.5 | D67: =D66*GETPIVOTDATA("Sum of Total Profit",$A$3) -> 488218.64 | E67: =E66*GETPIVOTDATA("Sum of Total Profit",$A$3) -> 1554303.9 | F67: =SUM(C67:E67) -> 3178565 | G67: % T-Bag units * Total-Profit
B68: Unit Profit per Bag | C68: =C67/C65 -> 3687.4519 | D68: =D67/D65 -> 3687.4519 | E68: =E67/E65 -> 3687.4519 | F68: =SUM(C68:E68) -> 11062.356 | G68: % worth on T-Profit / Block Type per Bags
B69: Block Qty per Bag | C69: 60 | D69: 50 | E69: 43 | F69: =SUM(C69:E69) -> 153 | G69: Block Qty per Bag
B70: % worth of Block Qty | C70: =C69/F69 -> 0.39215686 | D70: =D69/F69 -> 0.32679739 | E70: =E69/F69 -> 0.28104575 | F70: =SUM(C70:E70) -> 1 | G70: Block Qty per Bag / Total %
B71: Actual Profit per Bag | C71: =C70*F68 -> 4338.1788 | D71: =D70*F68 -> 3615.149 | E71: =E70*F68 -> 3109.0281 | F71: =SUM(C71:E71) -> 11062.356 | G71: % worth of Block Qty * Unit Profit per Bag
B72: Overall Profit per T-Bag units | C72: =C71*C65 -> 1336520.6 | D72: =D71*D65 -> 478645.72 | E72: =E71*E65 -> 1310491.5 | F72: =SUM(C72:E72) -> 3125657.8 | G72: Actual Profit per Bag * Block Type per T-Bags
B73: Difference of Total Profit | C73: =C67-C72 -> -200478.09 | D73: =D67-D72 -> 9572.9145 | E73: =E67-E72 -> 243812.37 | F73: =SUM(C73:E73) -> 52907.201 | G73: % worth on T-Profit - Overall Profit per T-Bag units
B74: %Block Qty of T-Profit Diff. | C74: =C70*F73 -> 20747.922 | D74: =D70*F73 -> 17289.935 | E74: =E70*F73 -> 14869.344 | F74: =SUM(C74:E74) -> 52907.201 | G74: % worth of Block Qty * TOTAL Difference of Total Profit
B75: PROFIT per Block Type Qty Sold | C75: =C74+C72 -> 1357268.5 | D75: =D74+D72 -> 495935.66 | E75: =E74+E72 -> 1325360.8 | F75: =SUM(C75:E75) -> 3178565 | G75: %Block Qty of T-Profit Diff. + Overall Profit per T-Bag units

Sheet OVERALL_TOTAL
A1: METRIC | B1: VALUE
A2: 6 Inches Qty Produced | B2: =SUM(PRODUCTION_DATA!B2:B50) -> 20598
A3: 7 Inches Qty Produced | B3: =SUM(PRODUCTION_DATA!C2:C50) -> 6663
A4: 9 Inches Qty Produced | B4: =SUM(PRODUCTION_DATA!D2:D50) -> 18618
A5: Total Qty Produced | B5: =SUM(PRODUCTION_DATA!E2:E50) -> 45879
A6: 6 Inches Qty Sold | B6: 18485
A7: 7 Inches Qty Sold | B7: 6620
A8: 9 Inches Qty Sold | B8: 18125
A9: Total Qty Sold | B9: =SUM(PRODUCTION_DATA!F2:F50) -> 43230
A10: Tons Of Sand | B10: =SUM(PRODUCTION_DATA!G2:G50) -> 1043
A11: Bags of Cement | B11: =SUM(PRODUCTION_DATA!H2:H50) -> 925
A12: Bag Produced | B12: =SUM(PRODUCTION_DATA!I2:I50) -> 916
A13: Ltr. Of Fuel | B13: =SUM(PRODUCTION_DATA!J2:J50) -> 690
A14: Total Cost | B14: =SUM(PRODUCTION_DATA!R2:R50) -> 15454975
A15: Total Amount | B15: =SUM(SALES__DATA!F2:F199) -> 18819310
A16: Total Revenue | B16: =SUM(PRODUCTION_DATA!Q2:Q50) -> 18633540
A17: Total Profit | B17: =SUM(PRODUCTION_DATA!S2:S50) -> 3178565
A18: Bad Debt | B18: =SUM(PRODUCTION_DATA!T2:T50) -> 185770
A19: VARIABLE COSTS
A20: Sand Cost | B20: =SUM(PRODUCTION_DATA!K2:K50) -> 5505000
A21: Cement Cost | B21: =SUM(PRODUCTION_DATA!L2:L50) -> 5157800
A22: Fuel Cost | B22: =SUM(PRODUCTION_DATA!N2:N50) -> 238455
A23: FIXED COSTS
A24: Operators' Payment | B24: =SUM(PRODUCTION_DATA!M2:M50) -> 1655700
A25: Maintenance | B25: =SUM(PRODUCTION_DATA!O2:O50) -> 534800
A26: Delivery Cost | B26: =SUM(PRODUCTION_DATA!P2:P50) -> 2364340
A27: RATES
A28: Production_Efficiency | B28: =B9/B5 -> 0.94226117
A29: Profit_Margin | B29: =B17/B16 -> 0.17058299
A30: Bad Debt_Rate | B30: =B18/B15 -> 0.009871244

Sheet KPI_DASHBOARD
A1: METRIC | B1: VALUE
A2: PRODUCTION KPIs
A3: 6 Inches Qty Produced | B3: =SUM(PRODUCTION_DATA!B2:B50) -> 20598
A4: 7 Inches Qty Produced | B4: =SUM(PRODUCTION_DATA!C2:C50) -> 6663
A5: 9 Inches Qty Produced | B5: =SUM(PRODUCTION_DATA!D2:D50) -> 18618
A6: Total Qty Produced | B6: =SUM(PRODUCTION_DATA!E2:E50) -> 45879
A7: Tons Of Sand | B7: =SUM(PRODUCTION_DATA!G2:G50) -> 1043
A8: Bags of Cement | B8: =SUM(PRODUCTION_DATA!H2:H50) -> 925
A9: Bag Produced | B9: =SUM(PRODUCTION_DATA!I2:I50) -> 916
A10: Ltr. Of Fuel | B10: =SUM(PRODUCTION_DATA!J2:J50) -> 690
A11: Production_Efficiency | B11: =B30/B6 -> 0.94226117
A12: Cost per Block | B12: =B19/B6 -> 336.86382
A13: Wastage Ratio% | B13: 0.038
A14: FINANCIAL KPIs
A15: Sand Cost | B15: =SUM(PRODUCTION_DATA!K2:K50) -> 5505000
A16: Cement Cost | B16: =SUM(PRODUCTION_DATA!L2:L50) -> 5157800
A17: Fuel Cost | B17: =SUM(PRODUCTION_DATA!N2:N50) -> 238455
A18: Operators' Payment | B18: =SUM(PRODUCTION_DATA!M2:M50) -> 1655700
A19: Total Cost | B19: =SUM(PRODUCTION_DATA!R2:R50) -> 15454975
A20: Total Amount | B20: =SUM(SALES__DATA!F2:F199) -> 18819310
A21: Total Revenue | B21: =SUM(PRODUCTION_DATA!Q2:Q50) -> 18633540
A22: Total Profit | B22: =SUM(PRODUCTION_DATA!S2:S50) -> 3178565
A23: Bad Debt | B23: =SUM(PRODUCTION_DATA!T2:T50) -> 185770
A24: Profit_Margin% | B24: =B22/B21 -> 0.17058299
A25: Bad Debt_Rate % | B25: =B23/B20 -> 0.009871244
A26: SALES KPIs
A27: 6 Inches Qty Sold | B27: 18485
A28: 7 Inches Qty Sold | B28: 6620
A29: 9 Inches Qty Sold | B29: 18125
A30: Total Qty Sold | B30: =SUM(PRODUCTION_DATA!F2:F50) -> 43230
A31: OPERATIONAL KPIs
A32: Maintenance | B32: =SUM(PRODUCTION_DATA!O2:O50) -> 534800
A33: Delivery Cost | B33: =SUM(PRODUCTION_DATA!P2:P50) -> 2364340

Sheet CHARTS
A3: Row Labels | B3: Sum of Qty Sold | C3: Sum of Revenue
A4: 6 Inches | B4: 18485 | C4: 8289700
A5: 7 Inches | B5: 6620 | C5: 2090500
A6: 9 Inches | B6: 18125 | C6: 8253340
A7: Grand Total | B7: 43230 | C7: 18633540
A9: Product Type | B9: Revenue | C9: PROFIT
A10: 6 Inches | B10: 8289700 | C10: 1357268.5
A11: 7 Inches | B11: 2090500 | C11: 495935.66
A12: 9 Inches | B12: 8253340 | C12: 1325360.8
A18: Row Labels | B18: Sum of Revenue
A19: 2022 | B19: 6068380
A20: 2023 | B20: 6556450
A21: 2024 | B21: 1790610
A22: 2025 | B22: 4218100
A23: Grand Total | B23: 18633540
A25: Year | B25: Total Revenue
A26: 2022 | B26: 6068380
A27: 2023 | B27: 6556450
A28: 2024 | B28: 1790610 | E28: Total Revenue
A29: 2025 | B29: 4218100
E30: 340250
E31: 347950
E32: 257600
E33: 521800
A34: Total Cost | B34: Total Profit | D34: Total Qty Sold | E34: 114700
A35: 276125 | B35: -276125 | E35: 222800
A36: 63700 | B36: 276550 | D36: 1274 | E36: 190000
A37: 472150 | B37: -124200 | D37: 1283 | E37: 1594000
A38: 255900 | B38: 1700 | D38: 802 | E38: 297980
A39: 340400 | B39: 181400 | D39: 1560 | E39: 1176300
A40: 115800 | B40: -1100 | D40: 376 | E40: 425000
A41: 261800 | B41: -39000 | D41: 706 | E41: 580000
A42: 142700 | B42: 47300 | D42: 600 | E42: 351320
A43: 1295200 | B43: 298800 | D43: 4600
A44: 444350 | B44: -146370 | D44: 954 | E44: 644100
A45: 1017500 | B45: 158800 | D45: 3460 | E45: 1015940
A46: 172000 | B46: 253000 | D46: 1150 | E46: 584200
A47: 511300 | B47: 68700 | D47: 1534 | E47: 343200
A48: 258900 | B48: 92420 | D48: 950 | E48: 181500
E49: 182200
A50: 568960 | B50: 75140 | D50: 1616 | E50: 841200
A51: 877290 | B51: 138650 | D51: 3381 | E51: 1255440
A52: 179420 | B52: 404780 | D52: 1642 | E52: 446900
A53: 442200 | B53: -99000 | D53: 870 | E53: 710450
A54: 360670 | B54: -179170 | D54: 470 | E54: 294000
A55: 275580 | B55: -93380 | D55: 440 | E55: 1120000
A56: 690830 | B56: 150370 | D56: 1928 | E56: 236350
A57: 971030 | B57: 284410 | D57: 2838 | E57: 129060
A58: 295620 | B58: 151280 | D58: 982
A59: 646250 | B59: 64200 | D59: 1505 | E59: 11200
A60: 105400 | B60: 188600 | D60: 720
A61: 935200 | B61: 184800 | D61: 2020
A62: 109290 | B62: 127060 | D62: 347
A63: 12110 | B63: 116950 | D63: 173
B65: 11200 | D65: 16
E71: 760000
E72: 762500
E73: 290300
E74: 436500
E75: 359700
A76: 814450 | B76: -814450 | E76: 885500
A77: 69375 | B77: 690625 | D77: 925 | E77: 723600
A78: 741250 | B78: 21250 | D78: 850
A79: 23550 | B79: 266750 | D79: 377
A80: 141250 | B80: 295250 | D80: 550
A81: 273450 | B81: 86250 | D81: 414
A82: 1235025 | B82: -349525 | D82: 1131
A83: 58950 | B83: 664650 | D83: 786
A88: Correlation Between Key Business Variables
A89: METRIC PAIR | B89: VALUE | C89: STRENGHT
A90: Production vs Sales | B90: =CORREL(PRODUCTION_DATA!E2:E50, PRODUCTION_DATA!F2:F50) -> 0.85450771 | C90: Strong Positive
A91: Production vs Cost | B91: =CORREL(PRODUCTION_DATA!E2:E50, PRODUCTION_DATA!R2:R50) -> 0.83464076 | C91: Strong Positive
A92: Production vs Revenue | B92: =CORREL(PRODUCTION_DATA!E2:E50, PRODUCTION_DATA!Q2:Q50) -> 0.81913693 | C92: Strong Positive
A93: Production vs Profit | B93: =CORREL(PRODUCTION_DATA!E2:E50, PRODUCTION_DATA!S2:S50) -> 0.090764254 | C93: Very Weak
A94: Cost vs Profit | B94: =CORREL(PRODUCTION_DATA!R2:R50, PRODUCTION_DATA!S2:S50) -> -0.2950324 | C94: Weak Negative
A95: Revenue vs Bad Debt | B95: =CORREL(PRODUCTION_DATA!Q2:Q50, PRODUCTION_DATA!T2:T50) -> 0.36733981 | C95: Moderate
